{
  "kind": "exercise",
  "exerciseName": "Decline Crunch Standards",
  "unit": "kg",
  "male": [
    {
      "level": "Beginner",
      "value": "< 1"
    },
    {
      "level": "Novice",
      "value": "11"
    },
    {
      "level": "Intermediate",
      "value": "29"
    },
    {
      "level": "Advanced",
      "value": "49"
    },
    {
      "level": "Elite",
      "value": "71"
    }
  ],
  "female": [
    {
      "level": "Beginner",
      "value": "< 1"
    },
    {
      "level": "Novice",
      "value": "10"
    },
    {
      "level": "Intermediate",
      "value": "33"
    },
    {
      "level": "Advanced",
      "value": "61"
    },
    {
      "level": "Elite",
      "value": "93"
    }
  ],
  "maleBodyweightRatio": [
    {
      "level": "Beginner",
      "value": "< 1"
    },
    {
      "level": "Novice",
      "value": "11"
    },
    {
      "level": "Intermediate",
      "value": "29"
    },
    {
      "level": "Advanced",
      "value": "49"
    },
    {
      "level": "Elite",
      "value": "71"
    }
  ],
  "femaleBodyweightRatio": [
    {
      "level": "Beginner",
      "value": "< 1"
    },
    {
      "level": "Novice",
      "value": "10"
    },
    {
      "level": "Intermediate",
      "value": "33"
    },
    {
      "level": "Advanced",
      "value": "61"
    },
    {
      "level": "Elite",
      "value": "93"
    }
  ],
  "maleByBodyweight": [
    {
      "label": "110",
      "beginner": "< 1",
      "novice": "17",
      "intermediate": "39",
      "advanced": "65",
      "elite": "94"
    },
    {
      "label": "120",
      "beginner": "< 1",
      "novice": "16",
      "intermediate": "37",
      "advanced": "61",
      "elite": "88"
    },
    {
      "label": "130",
      "beginner": "< 1",
      "novice": "15",
      "intermediate": "35",
      "advanced": "58",
      "elite": "84"
    },
    {
      "label": "140",
      "beginner": "< 1",
      "novice": "14",
      "intermediate": "33",
      "advanced": "55",
      "elite": "79"
    },
    {
      "label": "150",
      "beginner": "< 1",
      "novice": "13",
      "intermediate": "31",
      "advanced": "52",
      "elite": "75"
    },
    {
      "label": "160",
      "beginner": "< 1",
      "novice": "13",
      "intermediate": "30",
      "advanced": "50",
      "elite": "72"
    },
    {
      "label": "170",
      "beginner": "< 1",
      "novice": "12",
      "intermediate": "28",
      "advanced": "47",
      "elite": "68"
    },
    {
      "label": "180",
      "beginner": "< 1",
      "novice": "11",
      "intermediate": "27",
      "advanced": "45",
      "elite": "65"
    },
    {
      "label": "190",
      "beginner": "< 1",
      "novice": "10",
      "intermediate": "26",
      "advanced": "43",
      "elite": "62"
    },
    {
      "label": "200",
      "beginner": "< 1",
      "novice": "10",
      "intermediate": "24",
      "advanced": "41",
      "elite": "60"
    },
    {
      "label": "210",
      "beginner": "< 1",
      "novice": "9",
      "intermediate": "23",
      "advanced": "40",
      "elite": "57"
    },
    {
      "label": "220",
      "beginner": "< 1",
      "novice": "9",
      "intermediate": "22",
      "advanced": "38",
      "elite": "55"
    },
    {
      "label": "230",
      "beginner": "< 1",
      "novice": "8",
      "intermediate": "21",
      "advanced": "36",
      "elite": "53"
    },
    {
      "label": "240",
      "beginner": "< 1",
      "novice": "8",
      "intermediate": "20",
      "advanced": "35",
      "elite": "51"
    },
    {
      "label": "250",
      "beginner": "< 1",
      "novice": "7",
      "intermediate": "19",
      "advanced": "33",
      "elite": "49"
    },
    {
      "label": "260",
      "beginner": "< 1",
      "novice": "7",
      "intermediate": "18",
      "advanced": "32",
      "elite": "47"
    },
    {
      "label": "270",
      "beginner": "< 1",
      "novice": "7",
      "intermediate": "17",
      "advanced": "31",
      "elite": "45"
    },
    {
      "label": "280",
      "beginner": "< 1",
      "novice": "6",
      "intermediate": "16",
      "advanced": "30",
      "elite": "44"
    },
    {
      "label": "290",
      "beginner": "< 1",
      "novice": "6",
      "intermediate": "16",
      "advanced": "29",
      "elite": "42"
    },
    {
      "label": "300",
      "beginner": "< 1",
      "novice": "5",
      "intermediate": "15",
      "advanced": "27",
      "elite": "41"
    },
    {
      "label": "310",
      "beginner": "< 1",
      "novice": "5",
      "intermediate": "14",
      "advanced": "26",
      "elite": "39"
    }
  ],
  "femaleByBodyweight": [
    {
      "label": "90",
      "beginner": "< 1",
      "novice": "9",
      "intermediate": "36",
      "advanced": "70",
      "elite": "109"
    },
    {
      "label": "100",
      "beginner": "< 1",
      "novice": "10",
      "intermediate": "35",
      "advanced": "67",
      "elite": "104"
    },
    {
      "label": "110",
      "beginner": "< 1",
      "novice": "10",
      "intermediate": "35",
      "advanced": "65",
      "elite": "99"
    },
    {
      "label": "120",
      "beginner": "< 1",
      "novice": "10",
      "intermediate": "34",
      "advanced": "63",
      "elite": "95"
    },
    {
      "label": "130",
      "beginner": "< 1",
      "novice": "11",
      "intermediate": "33",
      "advanced": "60",
      "elite": "91"
    },
    {
      "label": "140",
      "beginner": "< 1",
      "novice": "11",
      "intermediate": "32",
      "advanced": "58",
      "elite": "88"
    },
    {
      "label": "150",
      "beginner": "< 1",
      "novice": "11",
      "intermediate": "31",
      "advanced": "56",
      "elite": "84"
    },
    {
      "label": "160",
      "beginner": "< 1",
      "novice": "10",
      "intermediate": "30",
      "advanced": "54",
      "elite": "81"
    },
    {
      "label": "170",
      "beginner": "< 1",
      "novice": "10",
      "intermediate": "30",
      "advanced": "53",
      "elite": "78"
    },
    {
      "label": "180",
      "beginner": "< 1",
      "novice": "10",
      "intermediate": "29",
      "advanced": "51",
      "elite": "75"
    },
    {
      "label": "190",
      "beginner": "< 1",
      "novice": "10",
      "intermediate": "28",
      "advanced": "49",
      "elite": "73"
    },
    {
      "label": "200",
      "beginner": "< 1",
      "novice": "10",
      "intermediate": "27",
      "advanced": "48",
      "elite": "70"
    },
    {
      "label": "210",
      "beginner": "< 1",
      "novice": "10",
      "intermediate": "26",
      "advanced": "46",
      "elite": "68"
    },
    {
      "label": "220",
      "beginner": "< 1",
      "novice": "9",
      "intermediate": "25",
      "advanced": "45",
      "elite": "66"
    },
    {
      "label": "230",
      "beginner": "< 1",
      "novice": "9",
      "intermediate": "24",
      "advanced": "43",
      "elite": "64"
    },
    {
      "label": "240",
      "beginner": "< 1",
      "novice": "9",
      "intermediate": "24",
      "advanced": "42",
      "elite": "62"
    },
    {
      "label": "250",
      "beginner": "< 1",
      "novice": "9",
      "intermediate": "23",
      "advanced": "41",
      "elite": "60"
    },
    {
      "label": "260",
      "beginner": "< 1",
      "novice": "8",
      "intermediate": "22",
      "advanced": "40",
      "elite": "58"
    }
  ],
  "maleByAge": [
    {
      "label": "15",
      "beginner": "< 1",
      "novice": "7",
      "intermediate": "20",
      "advanced": "38",
      "elite": "56"
    },
    {
      "label": "20",
      "beginner": "< 1",
      "novice": "10",
      "intermediate": "27",
      "advanced": "47",
      "elite": "69"
    },
    {
      "label": "25",
      "beginner": "< 1",
      "novice": "11",
      "intermediate": "29",
      "advanced": "49",
      "elite": "71"
    },
    {
      "label": "30",
      "beginner": "< 1",
      "novice": "11",
      "intermediate": "29",
      "advanced": "49",
      "elite": "71"
    },
    {
      "label": "35",
      "beginner": "< 1",
      "novice": "11",
      "intermediate": "29",
      "advanced": "49",
      "elite": "71"
    },
    {
      "label": "40",
      "beginner": "< 1",
      "novice": "11",
      "intermediate": "29",
      "advanced": "49",
      "elite": "71"
    },
    {
      "label": "45",
      "beginner": "< 1",
      "novice": "10",
      "intermediate": "26",
      "advanced": "45",
      "elite": "66"
    },
    {
      "label": "50",
      "beginner": "< 1",
      "novice": "8",
      "intermediate": "22",
      "advanced": "40",
      "elite": "60"
    },
    {
      "label": "55",
      "beginner": "< 1",
      "novice": "5",
      "intermediate": "18",
      "advanced": "35",
      "elite": "53"
    },
    {
      "label": "60",
      "beginner": "< 1",
      "novice": "2",
      "intermediate": "14",
      "advanced": "29",
      "elite": "46"
    },
    {
      "label": "65",
      "beginner": "< 1",
      "novice": "< 1",
      "intermediate": "10",
      "advanced": "24",
      "elite": "39"
    },
    {
      "label": "70",
      "beginner": "< 1",
      "novice": "< 1",
      "intermediate": "7",
      "advanced": "18",
      "elite": "32"
    },
    {
      "label": "75",
      "beginner": "< 1",
      "novice": "< 1",
      "intermediate": "3",
      "advanced": "13",
      "elite": "25"
    },
    {
      "label": "80",
      "beginner": "< 1",
      "novice": "< 1",
      "intermediate": "< 1",
      "advanced": "9",
      "elite": "20"
    },
    {
      "label": "85",
      "beginner": "< 1",
      "novice": "< 1",
      "intermediate": "< 1",
      "advanced": "6",
      "elite": "15"
    },
    {
      "label": "90",
      "beginner": "< 1",
      "novice": "< 1",
      "intermediate": "< 1",
      "advanced": "2",
      "elite": "10"
    }
  ],
  "femaleByAge": [
    {
      "label": "15",
      "beginner": "< 1",
      "novice": "5",
      "intermediate": "23",
      "advanced": "48",
      "elite": "75"
    },
    {
      "label": "20",
      "beginner": "< 1",
      "novice": "9",
      "intermediate": "31",
      "advanced": "59",
      "elite": "90"
    },
    {
      "label": "25",
      "beginner": "< 1",
      "novice": "10",
      "intermediate": "33",
      "advanced": "61",
      "elite": "93"
    },
    {
      "label": "30",
      "beginner": "< 1",
      "novice": "10",
      "intermediate": "33",
      "advanced": "61",
      "elite": "93"
    },
    {
      "label": "35",
      "beginner": "< 1",
      "novice": "10",
      "intermediate": "33",
      "advanced": "61",
      "elite": "93"
    },
    {
      "label": "40",
      "beginner": "< 1",
      "novice": "10",
      "intermediate": "33",
      "advanced": "61",
      "elite": "93"
    },
    {
      "label": "45",
      "beginner": "< 1",
      "novice": "8",
      "intermediate": "29",
      "advanced": "56",
      "elite": "87"
    },
    {
      "label": "50",
      "beginner": "< 1",
      "novice": "6",
      "intermediate": "25",
      "advanced": "51",
      "elite": "79"
    },
    {
      "label": "55",
      "beginner": "< 1",
      "novice": "4",
      "intermediate": "21",
      "advanced": "44",
      "elite": "71"
    },
    {
      "label": "60",
      "beginner": "< 1",
      "novice": "< 1",
      "intermediate": "17",
      "advanced": "38",
      "elite": "62"
    },
    {
      "label": "65",
      "beginner": "< 1",
      "novice": "< 1",
      "intermediate": "12",
      "advanced": "32",
      "elite": "53"
    },
    {
      "label": "70",
      "beginner": "< 1",
      "novice": "< 1",
      "intermediate": "9",
      "advanced": "25",
      "elite": "45"
    },
    {
      "label": "75",
      "beginner": "< 1",
      "novice": "< 1",
      "intermediate": "6",
      "advanced": "20",
      "elite": "37"
    },
    {
      "label": "80",
      "beginner": "< 1",
      "novice": "< 1",
      "intermediate": "2",
      "advanced": "15",
      "elite": "30"
    },
    {
      "label": "85",
      "beginner": "< 1",
      "novice": "< 1",
      "intermediate": "< 1",
      "advanced": "10",
      "elite": "24"
    },
    {
      "label": "90",
      "beginner": "< 1",
      "novice": "< 1",
      "intermediate": "< 1",
      "advanced": "7",
      "elite": "19"
    }
  ]
}
