{
  "kind": "comparison",
  "leftName": "Dumbbell Bulgarian Split Squat",
  "rightName": "Bulgarian Split Squat",
  "unit": "lb",
  "male": [
    {
      "level": "Beginner",
      "leftValue": "22 lb",
      "rightValue": "32 lb"
    },
    {
      "level": "Novice",
      "leftValue": "40 lb",
      "rightValue": "73 lb"
    },
    {
      "level": "Intermediate",
      "leftValue": "65 lb",
      "rightValue": "135 lb"
    },
    {
      "level": "Advanced",
      "leftValue": "97 lb",
      "rightValue": "216 lb"
    },
    {
      "level": "Elite",
      "leftValue": "132 lb",
      "rightValue": "310 lb"
    }
  ],
  "female": [
    {
      "level": "Beginner",
      "leftValue": "13 lb",
      "rightValue": "20 lb"
    },
    {
      "level": "Novice",
      "leftValue": "24 lb",
      "rightValue": "43 lb"
    },
    {
      "level": "Intermediate",
      "leftValue": "39 lb",
      "rightValue": "76 lb"
    },
    {
      "level": "Advanced",
      "leftValue": "58 lb",
      "rightValue": "117 lb"
    },
    {
      "level": "Elite",
      "leftValue": "80 lb",
      "rightValue": "166 lb"
    }
  ]
}
